alphaDeesp/Expert_rule_action_verification.py
alphaDeesp/__init__.py
alphaDeesp/expert_operator.py
alphaDeesp/main.py
alphaDeesp/core/__init__.py
alphaDeesp/core/alphadeesp.py
alphaDeesp/core/elements.py
alphaDeesp/core/graphsAndPaths.py
alphaDeesp/core/network.py
alphaDeesp/core/printer.py
alphaDeesp/core/simulation.py
alphaDeesp/core/grid2op/Grid2opObservationLoader.py
alphaDeesp/core/grid2op/Grid2opSimulation.py
alphaDeesp/core/grid2op/__init__.py
alphaDeesp/core/pypownet/PypownetObservationLoader.py
alphaDeesp/core/pypownet/PypownetSimulation.py
alphaDeesp/core/pypownet/__init__.py
alphaDeesp/ressources/config/config.ini
alphaDeesp/ressources/parameters/l2rpn_2019/config.py
alphaDeesp/ressources/parameters/l2rpn_2019/difficulty_levels.json
alphaDeesp/ressources/parameters/l2rpn_2019/grid.json
alphaDeesp/ressources/parameters/l2rpn_2019/grid_layout.json
alphaDeesp/ressources/parameters/l2rpn_2019/prods_charac.csv
alphaDeesp/ressources/parameters/l2rpn_2019/chronics/a/datetimes.csv
alphaDeesp/ressources/parameters/l2rpn_2019/chronics/a/hazards.zip
alphaDeesp/ressources/parameters/l2rpn_2019/chronics/a/imaps.csv
alphaDeesp/ressources/parameters/l2rpn_2019/chronics/a/load_p.zip
alphaDeesp/ressources/parameters/l2rpn_2019/chronics/a/load_p_forecasted.zip
alphaDeesp/ressources/parameters/l2rpn_2019/chronics/a/load_q.zip
alphaDeesp/ressources/parameters/l2rpn_2019/chronics/a/load_q_forecasted.zip
alphaDeesp/ressources/parameters/l2rpn_2019/chronics/a/maintenance.zip
alphaDeesp/ressources/parameters/l2rpn_2019/chronics/a/prod_p.zip
alphaDeesp/ressources/parameters/l2rpn_2019/chronics/a/prod_p_forecasted.zip
alphaDeesp/ressources/parameters/l2rpn_2019/chronics/a/prods_p.csv
alphaDeesp/ressources/parameters/l2rpn_2019/chronics/a/simu_ids.csv
alphaDeesp/tests/__init__.py
alphaDeesp/tests/alphadeesp_test.py
alphaDeesp/tests/test_cli.py
alphaDeesp/tests/test_expert_op.py
alphaDeesp/tests/test_expert_rules.py
alphaDeesp/tests/grid2op/__init__.py
expertop4grid-0.2.8.dist-info/licenses/LICENSE
expertop4grid-0.2.8.dist-info/licenses/LICENSE.md
expertop4grid-0.2.8.dist-info/METADATA
expertop4grid-0.2.8.dist-info/WHEEL
expertop4grid-0.2.8.dist-info/entry_points.txt
expertop4grid-0.2.8.dist-info/top_level.txt
expertop4grid-0.2.8.dist-info/RECORD
